{"mean":{"confidence_interval":{"confidence_level":0.95,"lower_bound":88588726.39416666,"upper_bound":88611865.92718253},"point_estimate":88601164.46634921,"standard_error":5992.799921922393},"median":{"confidence_interval":{"confidence_level":0.95,"lower_bound":88591286.58333333,"upper_bound":88616228.15},"point_estimate":88603194.27083334,"standard_error":7621.689304269237},"median_abs_dev":{"confidence_interval":{"confidence_level":0.95,"lower_bound":4676.336529493159,"upper_bound":33308.492546170775},"point_estimate":18462.755697224246,"standard_error":6811.722368622245},"slope":{"confidence_interval":{"confidence_level":0.95,"lower_bound":88586297.1090604,"upper_bound":88611002.6372796},"point_estimate":88599964.54675324,"standard_error":6381.550932393338},"std_dev":{"confidence_interval":{"confidence_level":0.95,"lower_bound":9765.872183773758,"upper_bound":27301.938014647265},"point_estimate":20112.530780732697,"standard_error":4970.321513711494}}