{"mean":{"confidence_interval":{"confidence_level":0.95,"lower_bound":102246877.96448413,"upper_bound":106132756.63339286},"point_estimate":104353969.1411508,"standard_error":1000957.2456902699},"median":{"confidence_interval":{"confidence_level":0.95,"lower_bound":102817127.95833334,"upper_bound":106790600.5},"point_estimate":104829712.3125,"standard_error":917404.6458607474},"median_abs_dev":{"confidence_interval":{"confidence_level":0.95,"lower_bound":629127.2803182596,"upper_bound":4769076.946698636},"point_estimate":2424956.7843650803,"standard_error":1052999.2302021268},"slope":{"confidence_interval":{"confidence_level":0.95,"lower_bound":103964315.84923077,"upper_bound":107435696.38441506},"point_estimate":105702647.46493506,"standard_error":938452.9422384488},"std_dev":{"confidence_interval":{"confidence_level":0.95,"lower_bound":1295548.88703946,"upper_bound":4657463.585223944},"point_estimate":3327636.29433657,"standard_error":947172.4040366486}}