{"mean":{"confidence_interval":{"confidence_level":0.95,"lower_bound":50369900.997142866,"upper_bound":65498233.05666666},"point_estimate":57943876.91023809,"standard_error":3873675.2852680725},"median":{"confidence_interval":{"confidence_level":0.95,"lower_bound":48774837.692857146,"upper_bound":68055698.0},"point_estimate":56138906.33333333,"standard_error":5197242.352431863},"median_abs_dev":{"confidence_interval":{"confidence_level":0.95,"lower_bound":1241026.4400673758,"upper_bound":21094268.04222688},"point_estimate":15404756.975860901,"standard_error":5233285.748951468},"slope":{"confidence_interval":{"confidence_level":0.95,"lower_bound":53150036.654255316,"upper_bound":66846851.07868335},"point_estimate":60929368.59220779,"standard_error":3503935.1571534956},"std_dev":{"confidence_interval":{"confidence_level":0.95,"lower_bound":7267128.444828462,"upper_bound":16337779.217397315},"point_estimate":12844892.936710786,"standard_error":2315955.5636461936}}