{"mean":{"confidence_interval":{"confidence_level":0.95,"lower_bound":109060640.05832641,"upper_bound":116293288.54229563},"point_estimate":112845906.18234126,"standard_error":1856934.0784679635},"median":{"confidence_interval":{"confidence_level":0.95,"lower_bound":107672093.66666667,"upper_bound":116563641.9875},"point_estimate":113370516.02142859,"standard_error":1715520.2768589365},"median_abs_dev":{"confidence_interval":{"confidence_level":0.95,"lower_bound":160027.7392989412,"upper_bound":11588657.96984769},"point_estimate":2782808.11113859,"standard_error":2936436.718035495},"slope":{"confidence_interval":{"confidence_level":0.95,"lower_bound":112461758.41336402,"upper_bound":116295295.33474576},"point_estimate":114421513.2,"standard_error":991148.0322032829},"std_dev":{"confidence_interval":{"confidence_level":0.95,"lower_bound":2467464.4555816664,"upper_bound":8040330.845223051},"point_estimate":6191797.444197871,"standard_error":1363344.9166791756}}