{"mean":{"confidence_interval":{"confidence_level":0.95,"lower_bound":607564386.1,"upper_bound":697720716.2},"point_estimate":653164906.2,"standard_error":23010529.481115717},"median":{"confidence_interval":{"confidence_level":0.95,"lower_bound":606324085.5,"upper_bound":695422601.0},"point_estimate":651790730.0,"standard_error":16590247.045103528},"median_abs_dev":{"confidence_interval":{"confidence_level":0.95,"lower_bound":4519289.4091665745,"upper_bound":130010476.36475265},"point_estimate":26458877.20836103,"standard_error":40787293.59769141},"slope":null,"std_dev":{"confidence_interval":{"confidence_level":0.95,"lower_bound":32914748.730780914,"upper_bound":102830062.03322566},"point_estimate":76356461.30377923,"standard_error":17548083.845655296}}