{"mean":{"confidence_interval":{"confidence_level":0.95,"lower_bound":108285128.93373811,"upper_bound":115607815.25255355},"point_estimate":111988946.9597619,"standard_error":1876953.3662211027},"median":{"confidence_interval":{"confidence_level":0.95,"lower_bound":106328732.71428572,"upper_bound":117361714.16666666},"point_estimate":112818627.15,"standard_error":2271930.074667375},"median_abs_dev":{"confidence_interval":{"confidence_level":0.95,"lower_bound":854774.4293747236,"upper_bound":10880819.183351845},"point_estimate":6294969.438531959,"standard_error":3025424.8532415335},"slope":{"confidence_interval":{"confidence_level":0.95,"lower_bound":108966442.45643154,"upper_bound":113388106.01491503},"point_estimate":111652191.38181818,"standard_error":1132634.189609388},"std_dev":{"confidence_interval":{"confidence_level":0.95,"lower_bound":3457380.293124432,"upper_bound":7857749.0717442455},"point_estimate":6199265.709764064,"standard_error":1142898.5774274599}}