{"mean":{"confidence_interval":{"confidence_level":0.95,"lower_bound":21093994.53222222,"upper_bound":21156369.437722225},"point_estimate":21122707.24489682,"standard_error":16058.767675240442},"median":{"confidence_interval":{"confidence_level":0.95,"lower_bound":21083568.942857143,"upper_bound":21174485.08},"point_estimate":21098281.455555554,"standard_error":22950.411461257223},"median_abs_dev":{"confidence_interval":{"confidence_level":0.95,"lower_bound":6139.66888099964,"upper_bound":84226.26728868463},"point_estimate":30515.09504824932,"standard_error":21065.159490188365},"slope":{"confidence_interval":{"confidence_level":0.95,"lower_bound":21093277.139820065,"upper_bound":21169250.501940034},"point_estimate":21135912.267532468,"standard_error":18713.612080479466},"std_dev":{"confidence_interval":{"confidence_level":0.95,"lower_bound":18441.543327920914,"upper_bound":68586.35131752085},"point_estimate":53307.31873631789,"standard_error":11926.610670045953}}